revival/__init__.py
revival/base.py
revival/loading_model.py
revival-2025.3.1.dist-info/licenses/LICENSE
utils/__init__.py
utils/utils.py
revival-2025.3.1.dist-info/METADATA
revival-2025.3.1.dist-info/WHEEL
revival-2025.3.1.dist-info/top_level.txt
revival-2025.3.1.dist-info/RECORD
