Metadata-Version: 2.4
Name: revivAl
Version: 2025.3.1
Author-email: Fatma Baraket <fatma.baraket@mews-labs.com>
Project-URL: Homepage, https://github.com/eurobios-mews-labs/revival
Requires-Python: >=3.6
License-File: LICENSE
Requires-Dist: h5py>3
Requires-Dist: scikit-learn
Requires-Dist: tensorflow
Requires-Dist: catboost
Provides-Extra: examples
Requires-Dist: matplotlib~=3.9.2; extra == "examples"
Provides-Extra: test
Requires-Dist: catboost; extra == "test"
Requires-Dist: numpy; extra == "test"
Requires-Dist: pandas; extra == "test"
Requires-Dist: pytest; extra == "test"
Requires-Dist: pytest-cov; extra == "test"
Requires-Dist: pylint; extra == "test"
Provides-Extra: lint
Requires-Dist: black; extra == "lint"
Requires-Dist: mypy; extra == "lint"
Requires-Dist: ruff; extra == "lint"
Provides-Extra: dev
Requires-Dist: revival[lint,test]; extra == "dev"
Dynamic: license-file
